holmes/__init__.py
holmes/dataloader.py
holmes/features.py
holmes/test_run.py
holmes_ml-0.0.1.dist-info/METADATA
holmes_ml-0.0.1.dist-info/RECORD
holmes_ml-0.0.1.dist-info/WHEEL
holmes_ml-0.0.1.dist-info/top_level.txt
